impact/__init__.py
impact/impact.py
impact/network/__init__.py
impact/network/classifiers.py
impact/network/torch_train.py
impact/network/utils.py
impact/utils/__init__.py
impact/utils/feature_selection.py
impact/utils/image_transformer.py
impact/utils/plot.py
IMPACTBIOINFORMATICS-4.6.dist-info/METADATA
IMPACTBIOINFORMATICS-4.6.dist-info/WHEEL
IMPACTBIOINFORMATICS-4.6.dist-info/top_level.txt
IMPACTBIOINFORMATICS-4.6.dist-info/RECORD
