Metadata-Version: 2.1
Name: IMPACTBIOINFORMATICS
Version: 4.6
Summary: IMPACT: Interpretable Microbial Phenotype Analysis via microbial Characteristic Traits
Home-page: https://github.com/Wenze18/IMPACT.git
Author: USYD precision medicine center
Author-email: wenze.ding@sydney.edu.au
Classifier: Programming Language :: Python :: 3
Classifier: License :: OSI Approved :: MIT License
Classifier: Operating System :: OS Independent
Requires-Python: >=3.6
Requires-Dist: pandas
Requires-Dist: numpy
Requires-Dist: torch
Requires-Dist: torchvision
Requires-Dist: scikit-learn
Requires-Dist: umap
Requires-Dist: grad-cam
Requires-Dist: torchcam
